locmem/__init__.py
locmem/core.py
locmem/datatype.py
locmem/allocator/__init__.py
locmem/allocator/base.py
locmem/allocator/binned.py
locmem/allocator/heap.py
locmem/allocator/libc_malloc.py
locmem/allocator/mimalloc.py
locmem/allocator/tcmalloc.py
locmem/os_mem/__init__.py
locmem/os_mem/base.py
locmem/os_mem/posix.py
locmem/os_mem/win32.py
locmem-0.1.2.dist-info/METADATA
locmem-0.1.2.dist-info/WHEEL
locmem-0.1.2.dist-info/top_level.txt
locmem-0.1.2.dist-info/RECORD
