Metadata-Version: 2.4
Name: locmem
Version: 0.1.2
Summary: A Python library for direct, low-level memory management.
Author-email: MoYan <moyan@moyanjdc.top>
License: MIT License
Project-URL: Homepage, https://github.com/moyanj/locmem
Project-URL: Repository, https://github.com/moyanj/locmem
Project-URL: Bug Tracker, https://github.com/moyanj/locmem/issues
Keywords: memory,low-level,pointer,ctypes,mmap,virtualalloc,memory management
Classifier: Development Status :: 3 - Alpha
Classifier: Intended Audience :: Developers
Classifier: Topic :: Software Development :: Libraries :: Python Modules
Classifier: License :: OSI Approved :: MIT License
Classifier: Operating System :: Microsoft :: Windows
Classifier: Operating System :: POSIX :: Linux
Classifier: Operating System :: MacOS
Classifier: Programming Language :: Python :: 3
Classifier: Programming Language :: Python :: 3.8
Classifier: Programming Language :: Python :: 3.9
Classifier: Programming Language :: Python :: 3.10
Classifier: Programming Language :: Python :: 3.11
Classifier: Programming Language :: Python :: 3.12
Classifier: Programming Language :: Python :: 3.13
Requires-Python: >=3.8
Provides-Extra: dev
Requires-Dist: black; extra == "dev"
